baiji/__init__.py
baiji/pod/__init__.py
baiji/pod/asset_cache.py
baiji/pod/asset_pack.py
baiji/pod/config.py
baiji/pod/package_version.py
baiji/pod/prefill.py
baiji/pod/test_asset_cache.py
baiji/pod/runners/__init__.py
baiji/pod/runners/asset_pack_runner.py
baiji/pod/runners/cache_util_runner.py
baiji/pod/runners/prefill_runner.py
baiji/pod/runners/test_cache_util_runner.py
baiji/pod/runners/vc_runner.py
baiji/pod/util/__init__.py
baiji/pod/util/format_bytes.py
baiji/pod/util/json.py
baiji/pod/util/reachability.py
baiji/pod/util/shutillib.py
baiji/pod/util/yaml.py
baiji/pod/versioned/__init__.py
baiji/pod/versioned/core.py
baiji/pod/versioned/test_core.py
baiji/pod/versioned/uploader.py
baiji_pod-1.0.6.data/scripts/baiji-cache
baiji_pod-1.0.6.data/scripts/baiji-pack
baiji_pod-1.0.6.data/scripts/baiji-prefill
baiji_pod-1.0.6.data/scripts/vc
baiji_pod-1.0.6.dist-info/DESCRIPTION.rst
baiji_pod-1.0.6.dist-info/METADATA
baiji_pod-1.0.6.dist-info/RECORD
baiji_pod-1.0.6.dist-info/WHEEL
baiji_pod-1.0.6.dist-info/metadata.json
baiji_pod-1.0.6.dist-info/top_level.txt
