Metadata-Version: 2.0
Name: baiji-pod
Version: 1.0.6
Summary: Static caching of files from Amazon S3, using baiji
Home-page: https://github.com/bodylabs/baiji-pod
Author: Body Labs
Author-email: alex@bodylabs.com, paul.melnikow@bodylabs.com
License: Apache
Platform: UNKNOWN
Classifier: Development Status :: 3 - Alpha
Classifier: Intended Audience :: Developers
Classifier: License :: OSI Approved :: MIT License
Classifier: Operating System :: OS Independent
Classifier: Programming Language :: Python
Requires-Dist: baiji (>=2.2.9)
Requires-Dist: cached-property (<1.4,>=1.3.0)
Requires-Dist: env-flag (>=1.0.0,<2.0.0)
Requires-Dist: harrison (>=1.0.0,<2.0.0)
Requires-Dist: semantic-version (<2.5.0,>=2.4.2)
Requires-Dist: simplejson (>=3.8.2)
